decoder-bcd-7-segments/rt1/decoder.v
module decoder(
	 A, B, C, D, a, b, c, d, e ,f, g
	);

   //Structural Model

   //Inputs
   input wire A;
   input wire B;
   input wire C;
   input wire D;

   //Negateds Inputs
   input wire A_;
   input wire B_;
   input wire C_;
   input wire D_;


   //Outputs
   output wire a;
   output wire b;
   output wire c;
   output wire d;
   output wire e;
   output wire f;
   output wire g;

   //Inverted Signal Assignments
   assign A_ = ~A;
   assign B_ = ~B;
   assign C_ = ~C;
   assign D_ = ~D;

   //a Logic
   assign a = (A_ &((B & D) | C) | ((B_ & C_)&(A|D_)));

   //b Logic
   assign b = (B_ & C_) | (A_&(C ~^ D));

   //c Logic
   assign c = (A_&(B | C_ | D) | (B_ & C_));
  
   //d Logic
   assign d = (B_ & C_ & D_) | (A_&((B_ & C) | (C & D_) | (B & C_ & D)));

   //e Logic
   assign e = (D_&((A_ & C) | ~(B | C)));

   //f Logic
   assign f = (C_&((A & B_) | (A_ & B) | (B_ & D_)) | (A_ & B & D_));

   //g Logic
   assign g = (A & B_ & C_) | A_&((B & C_) | (B_ & C) | (C & D_));

endmodule

decoder-bcd-7-segments/tb/decoder_tb.v
`timescale 1ns/1ps

module decoder_tb;

reg A;
reg B;
reg C;
reg D;

wire a;
wire b;
wire c;
wire d;
wire e;
wire f;
wire g;

decoder dut(
    .A(A),
    .B(B),
    .C(C),
    .D(D),
    .a(a),
    .b(b),
    .c(c),
    .d(d),
    .e(e),
    .f(f),
    .g(g)
);

initial begin
    $dumpfile("decoder.vcd");
    $dumpvars(0, decoder_tb);

    $display(" A B C D | a b c d e f g");
    $monitor(" %b %b %b %b | %b %b %b %b %b %b %b", A, B, C, D, a, b, c, d, e, f, g);

    A = 0; B = 0; C = 0; D = 0; #20;
    A = 0; B = 0; C = 0; D = 1; #20;
    A = 0; B = 0; C = 1; D = 0; #20;
    A = 0; B = 0; C = 1; D = 1; #20;
    A = 0; B = 1; C = 0; D = 0; #20;
    A = 0; B = 1; C = 0; D = 1; #20;
    A = 0; B = 1; C = 1; D = 0; #20;
    A = 0; B = 1; C = 1; D = 1; #20;
    A = 1; B = 0; C = 0; D = 0; #20;
    A = 1; B = 0; C = 0; D = 1; #20;

    $finish;
end

endmodule

decoder-bcd-7-segments/decoder.vcd
$date
	Wed Jul  9 09:41:27 2025
$end
$version
	Icarus Verilog
$end
$timescale
	1ps
$end
$scope module decoder_tb $end
$var wire 1 ! g $end
$var wire 1 " f $end
$var wire 1 # e $end
$var wire 1 $ d $end
$var wire 1 % c $end
$var wire 1 & b $end
$var wire 1 ' a $end
$var reg 1 ( A $end
$var reg 1 ) B $end
$var reg 1 * C $end
$var reg 1 + D $end
$scope module dut $end
$var wire 1 ( A $end
$var wire 1 , A_ $end
$var wire 1 ) B $end
$var wire 1 - B_ $end
$var wire 1 * C $end
$var wire 1 . C_ $end
$var wire 1 + D $end
$var wire 1 / D_ $end
$var wire 1 ' a $end
$var wire 1 & b $end
$var wire 1 % c $end
$var wire 1 $ d $end
$var wire 1 # e $end
$var wire 1 " f $end
$var wire 1 ! g $end
$upscope $end
$upscope $end
$enddefinitions $end
$comment Show the parameter values. $end
$dumpall
$end
#0
$dumpvars
1/
1.
1-
1,
0+
0*
0)
0(
1'
1&
1%
1$
1#
1"
0!
$end
#20000
0"
0'
0$
0#
0/
1+
#40000
0%
1$
1!
0&
1'
1#
1/
0.
0+
1*
#60000
1&
1%
0#
0/
1+
#80000
0$
1!
0'
1"
1/
1.
0-
0+
0*
1)
#100000
1'
1$
0&
0/
1+
#120000
1$
1#
1/
0.
0+
1*
#140000
0$
0!
0"
1&
0#
0/
1+
#160000
1$
1"
1!
1'
1#
1/
1.
1-
0,
0+
0*
0)
1(
#180000
0$
0#
0/
1+
